phenotype2phenopacket/__init__.py
phenotype2phenopacket/add/__init__.py
phenotype2phenopacket/add/add_genes.py
phenotype2phenopacket/cli.py
phenotype2phenopacket/cli_add.py
phenotype2phenopacket/cli_convert.py
phenotype2phenopacket/cli_create.py
phenotype2phenopacket/convert/__init__.py
phenotype2phenopacket/convert/convert.py
phenotype2phenopacket/create/__init__.py
phenotype2phenopacket/create/create.py
phenotype2phenopacket/resources/hgnc_complete_set_2023-04-01.txt
phenotype2phenopacket/utils/__init__.py
phenotype2phenopacket/utils/phenopacket_utils.py
phenotype2phenopacket/utils/utils.py
phenotype2phenopacket-0.6.16.dist-info/METADATA
phenotype2phenopacket-0.6.16.dist-info/WHEEL
phenotype2phenopacket-0.6.16.dist-info/entry_points.txt
phenotype2phenopacket-0.6.16.dist-info/RECORD
