Metadata-Version: 2.3
Name: phenotype2phenopacket
Version: 0.6.16
Summary: 
Author: Yasemin Bridges
Author-email: y.bridges@qmul.ac.uk
Requires-Python: >=3.10,<4.0
Classifier: Programming Language :: Python :: 3
Classifier: Programming Language :: Python :: 3.10
Classifier: Programming Language :: Python :: 3.11
Classifier: Programming Language :: Python :: 3.12
Classifier: Programming Language :: Python :: 3.13
Requires-Dist: click (>=8.1.3,<9.0.0)
Requires-Dist: oaklib (>=0.5.1,<0.6.0)
Requires-Dist: pandas (>=2.0.0,<3.0.0)
Requires-Dist: phenopackets (>=2.0.2,<3.0.0)
Requires-Dist: pheval (>=0.5.8,<0.6.0)
